meltano/__init__.py
meltano/py.typed
meltano/cli/__init__.py
meltano/cli/__main__.py
meltano/cli/_didyoumean.py
meltano/cli/add.py
meltano/cli/cli.py
meltano/cli/compile.py
meltano/cli/config.py
meltano/cli/docs.py
meltano/cli/dragon.py
meltano/cli/elt.py
meltano/cli/environment.py
meltano/cli/hub.py
meltano/cli/initialize.py
meltano/cli/install.py
meltano/cli/invoke.py
meltano/cli/job.py
meltano/cli/lock.py
meltano/cli/logs.py
meltano/cli/params.py
meltano/cli/remove.py
meltano/cli/run.py
meltano/cli/schedule.py
meltano/cli/schema.py
meltano/cli/select_entities.py
meltano/cli/state.py
meltano/cli/upgrade.py
meltano/cli/utils.py
meltano/cli/validate.py
meltano/cli/interactive/__init__.py
meltano/cli/interactive/config.py
meltano/cli/interactive/utils.py
meltano/core/__init__.py
meltano/core/_compat.py
meltano/core/_packaging.py
meltano/core/_state.py
meltano/core/_types.py
meltano/core/cli_messages.py
meltano/core/config_service.py
meltano/core/constants.py
meltano/core/db.py
meltano/core/elt_context.py
meltano/core/environment.py
meltano/core/environment_service.py
meltano/core/error.py
meltano/core/job_state.py
meltano/core/locked_definition_service.py
meltano/core/meltano_file.py
meltano/core/meltano_invoker.py
meltano/core/migration_service.py
meltano/core/models.py
meltano/core/plugin_install_service.py
meltano/core/plugin_invoker.py
meltano/core/plugin_location_remove.py
meltano/core/plugin_lock_service.py
meltano/core/plugin_remove_service.py
meltano/core/plugin_repository.py
meltano/core/plugin_test_service.py
meltano/core/project.py
meltano/core/project_add_service.py
meltano/core/project_dirs_service.py
meltano/core/project_files.py
meltano/core/project_init_service.py
meltano/core/project_plugins_service.py
meltano/core/project_settings_service.py
meltano/core/schedule.py
meltano/core/schedule_service.py
meltano/core/select_service.py
meltano/core/setting.py
meltano/core/setting_definition.py
meltano/core/settings_service.py
meltano-4.1.1.dist-info/METADATA
meltano-4.1.1.dist-info/WHEEL
meltano-4.1.1.dist-info/entry_points.txt
meltano-4.1.1.dist-info/licenses/LICENSE
meltano-4.1.1.dist-info/RECORD
