Metadata-Version: 2.4
Name: meltano
Version: 4.1.1
Summary: Meltano is your CLI for ELT+: Open Source, Flexible, and Scalable. Move, transform, and test your data with confidence using a streamlined data engineering workflow you’ll love.
Project-URL: Homepage, https://meltano.com
Project-URL: Repository, https://github.com/meltano/meltano
Project-URL: Documentation, https://docs.meltano.com
Project-URL: Changelog, https://github.com/meltano/meltano/blob/main/CHANGELOG.md
Project-URL: Issue Tracker, https://github.com/meltano/meltano/issues
Project-URL: Slack, https://meltano.com/slack
Project-URL: Twitter, https://twitter.com/meltanodata/
Project-URL: Youtube, https://www.youtube.com/meltano
Author-email: Meltano <hello@meltano.com>
License-Expression: MIT
License-File: LICENSE
Keywords: Data integration,ELT,Meltano,dbt,singer-io
Classifier: Development Status :: 5 - Production/Stable
Classifier: Operating System :: OS Independent
Classifier: Programming Language :: Python :: 3 :: Only
Classifier: Programming Language :: Python :: 3.10
Classifier: Programming Language :: Python :: 3.11
Classifier: Programming Language :: Python :: 3.12
Classifier: Programming Language :: Python :: 3.13
Classifier: Programming Language :: Python :: 3.14
Requires-Python: >=3.10
Requires-Dist: alembic<2,>=1.14.0
Requires-Dist: anyio<5,>=4.4.0
Requires-Dist: backports-strenum<2,>=1.3.1; python_version < '3.11'
Requires-Dist: click!=8.2.2,<8.4,>=8.1
Requires-Dist: click-default-group<2,>=1.2.4
Requires-Dist: dateparser>=1.2.1
Requires-Dist: fasteners<0.21,>=0.19
Requires-Dist: importlib-metadata>=5; python_version < '3.12'
Requires-Dist: jinja2<4,>=3.1.4
Requires-Dist: jsonschema<5,>=4.23
Requires-Dist: packaging<27.0,>=24.2
Requires-Dist: pip~=25.1
Requires-Dist: platformdirs>=4.3.8
Requires-Dist: psutil<8,>=7.0.0
Requires-Dist: python-dotenv<2,>=1.0.1
Requires-Dist: pyyaml<7,>=6.0.2
Requires-Dist: requests<3,>=2.32.3
Requires-Dist: rich<14.4,>=14.0
Requires-Dist: ruamel-yaml<0.20,>=0.18.6
Requires-Dist: smart-open<8,>=7.0.5
Requires-Dist: snowplow-tracker<2,>=1.0.4
Requires-Dist: sqlalchemy<2.1,>=2.0.35
Requires-Dist: structlog<26,>=25.5.0
Requires-Dist: typing-extensions<5,>=4.12.2
Requires-Dist: tzlocal~=5.3
Requires-Dist: urllib3>=1.26.20
Requires-Dist: uv!=0.8.7,<0.10,>=0.1.24
Requires-Dist: virtualenv<21,>=20.26.6
Provides-Extra: azure
Requires-Dist: azure-common<2,>=1.1.28; extra == 'azure'
Requires-Dist: azure-core<2,>=1.32.0; extra == 'azure'
Requires-Dist: azure-identity<2,>=1.19.0; extra == 'azure'
Requires-Dist: azure-storage-blob<13,>=12.24.0; extra == 'azure'
Provides-Extra: containers
Requires-Dist: aiodocker<0.26,>=0.24.0; extra == 'containers'
Provides-Extra: gcs
Requires-Dist: google-cloud-storage>=1.31.0; extra == 'gcs'
Provides-Extra: mssql
Requires-Dist: pymssql<3,>=2.3.2; extra == 'mssql'
Provides-Extra: postgres
Requires-Dist: psycopg[binary]<4,>=3.2.3; extra == 'postgres'
Provides-Extra: psycopg2
Requires-Dist: psycopg2-binary<3,>=2.9.9; extra == 'psycopg2'
Provides-Extra: s3
Requires-Dist: boto3<1.43,>=1.35; extra == 's3'
